mkr_format/__init__.py
mkr_format/_version.py
mkr_format/api_utils.py
mkr_format/mkr_format_pybind.cpython-39-darwin.so
mkr_format/reader.py
mkr_format/reader_pyarrow.py
mkr_format/reader_utils.py
mkr_format/signal_tools.py
mkr_format/utils.py
mkr_format/writer.py
mkr_format-0.0.13.dist-info/METADATA
mkr_format-0.0.13.dist-info/WHEEL
mkr_format-0.0.13.dist-info/top_level.txt
mkr_format-0.0.13.dist-info/RECORD
