Metadata-Version: 2.1
Name: mkr-format
Version: 0.0.13
Summary: Python bindings for the MKR file format
Home-page: http://www.nanoporetech.com
Author: Oxford Nanopore Technologies plc
Author-email: support@nanoporetech.com
License: UNKNOWN
Platform: UNKNOWN
Requires-Dist: iso8601
Requires-Dist: more-itertools
Requires-Dist: numpy
Requires-Dist: pyarrow (~=7.0.0)
Requires-Dist: pytz
